<annotation>
 <folder>LW11-2</folder>
 <filename>(2021-08-17)LW11_147_37.jpg</filename>
 <path>None</path>
 <source>
  <database>Unknown</database>
 </source>
 <size>
  <width>5472</width>
  <height>3648</height>
  <depth>3</depth>
 </size>
 <segmented>0</segmented>
 <object>
  <name>(11)PET_Bottle</name>
  <pose>Unspecified</pose>
  <truncated>0</truncated>
  <difficult>0</difficult>
  <bndbox>
   <xmin>374</xmin>
   <ymin>90</ymin>
   <xmax>437</xmax>
   <ymax>179</ymax>
  </bndbox>
 </object>
 <object>
  <name>(21)Styrofoam_Piece</name>
  <pose>Unspecified</pose>
  <truncated>0</truncated>
  <difficult>0</difficult>
  <bndbox>
   <xmin>274</xmin>
   <ymin>143</ymin>
   <xmax>317</xmax>
   <ymax>184</ymax>
  </bndbox>
 </object>
 <object>
  <name>(21)Styrofoam_Piece</name>
  <pose>Unspecified</pose>
  <truncated>0</truncated>
  <difficult>0</difficult>
  <bndbox>
   <xmin>428</xmin>
   <ymin>345</ymin>
   <xmax>478</xmax>
   <ymax>405</ymax>
  </bndbox>
 </object>
 <object>
  <name>(11)PET_Bottle</name>
  <pose>Unspecified</pose>
  <truncated>0</truncated>
  <difficult>0</difficult>
  <bndbox>
   <xmin>271</xmin>
   <ymin>442</ymin>
   <xmax>310</xmax>
   <ymax>505</ymax>
  </bndbox>
 </object>
 <object>
  <name>(11)PET_Bottle</name>
  <pose>Unspecified</pose>
  <truncated>0</truncated>
  <difficult>0</difficult>
  <bndbox>
   <xmin>379</xmin>
   <ymin>446</ymin>
   <xmax>406</xmax>
   <ymax>505</ymax>
  </bndbox>
 </object>
 <object>
  <name>(11)PET_Bottle</name>
  <pose>Unspecified</pose>
  <truncated>0</truncated>
  <difficult>0</difficult>
  <bndbox>
   <xmin>402</xmin>
   <ymin>458</ymin>
   <xmax>424</xmax>
   <ymax>523</ymax>
  </bndbox>
 </object>
 <object>
  <name>(22)Rope</name>
  <pose>Unspecified</pose>
  <truncated>0</truncated>
  <difficult>0</difficult>
  <bndbox>
   <xmin>474</xmin>
   <ymin>375</ymin>
   <xmax>605</xmax>
   <ymax>619</ymax>
  </bndbox>
 </object>
 <object>
  <name>(21)Styrofoam_Piece</name>
  <pose>Unspecified</pose>
  <truncated>0</truncated>
  <difficult>0</difficult>
  <bndbox>
   <xmin>621</xmin>
   <ymin>204</ymin>
   <xmax>652</xmax>
   <ymax>239</ymax>
  </bndbox>
 </object>
 <object>
  <name>(21)Styrofoam_Piece</name>
  <pose>Unspecified</pose>
  <truncated>0</truncated>
  <difficult>0</difficult>
  <bndbox>
   <xmin>649</xmin>
   <ymin>349</ymin>
   <xmax>681</xmax>
   <ymax>382</ymax>
  </bndbox>
 </object>
 <object>
  <name>(21)Styrofoam_Piece</name>
  <pose>Unspecified</pose>
  <truncated>0</truncated>
  <difficult>0</difficult>
  <bndbox>
   <xmin>869</xmin>
   <ymin>423</ymin>
   <xmax>892</xmax>
   <ymax>457</ymax>
  </bndbox>
 </object>
 <object>
  <name>(21)Styrofoam_Piece</name>
  <pose>Unspecified</pose>
  <truncated>0</truncated>
  <difficult>0</difficult>
  <bndbox>
   <xmin>686</xmin>
   <ymin>377</ymin>
   <xmax>719</xmax>
   <ymax>434</ymax>
  </bndbox>
 </object>
 <object>
  <name>(11)PET_Bottle</name>
  <pose>Unspecified</pose>
  <truncated>0</truncated>
  <difficult>0</difficult>
  <bndbox>
   <xmin>162</xmin>
   <ymin>174</ymin>
   <xmax>200</xmax>
   <ymax>240</ymax>
  </bndbox>
 </object>
 <object>
  <name>(11)PET_Bottle</name>
  <pose>Unspecified</pose>
  <truncated>0</truncated>
  <difficult>0</difficult>
  <bndbox>
   <xmin>976</xmin>
   <ymin>246</ymin>
   <xmax>1035</xmax>
   <ymax>287</ymax>
  </bndbox>
 </object>
 <date>2021-08-04</date>
 <time>09:02:33</time>
 <device>Phantom4Advanced</device>
 <camera>FC6310</camera>
 <shutter>0.008333</shutter>
 <altitude>15</altitude>
 <lat>36.13689519444444</lat>
 <lon>126.57815422222222</lon>
 <gtype>sand</gtype>
</annotation>